pelican/plugins/aio_planet/__init__.py
pelican/plugins/aio_planet/_version.py
pelican/plugins/aio_planet/planet.py
pelican/plugins/aio_planet/utils.py
pelican_aio_planet-0.10.2.dist-info/METADATA
pelican_aio_planet-0.10.2.dist-info/WHEEL
pelican_aio_planet-0.10.2.dist-info/licenses/COPYING
pelican_aio_planet-0.10.2.dist-info/RECORD
