Metadata-Version: 2.3
Name: pelican-aio-planet
Version: 0.10.2
Summary: Asyncio powered log aggregator plugin for Pelican
Project-URL: Homepage, https://codeberg.org/ashwinvis/pelican-aio-planet
Author-email: Ashwin Vishnu <dev@fluid.quest>
License-Expression: AGPL-3.0-or-later
License-File: COPYING
Classifier: Development Status :: 4 - Beta
Classifier: Framework :: Pelican :: Plugins
Classifier: License :: OSI Approved :: GNU Affero General Public License v3 or later (AGPLv3+)
Classifier: Programming Language :: Python :: 3 :: Only
Classifier: Programming Language :: Python :: 3.7
Classifier: Programming Language :: Python :: 3.8
Classifier: Programming Language :: Python :: 3.9
Classifier: Programming Language :: Python :: 3.10
Classifier: Programming Language :: Python :: 3.11
Classifier: Topic :: Internet :: WWW/HTTP
Classifier: Topic :: Internet :: WWW/HTTP :: Site Management
Requires-Python: >=3.7
Requires-Dist: aiohttp-client-cache[sqlite]<0.13.0,>=0.5.1
Requires-Dist: aiohttp>=3.7.4.post0
Requires-Dist: async-timeout>=4.0.3
Requires-Dist: bleach>=4.1.0
Requires-Dist: feedparser>=6.0.0
Requires-Dist: jinja2>=2.11.1
Requires-Dist: pelican>=4.5.0
Requires-Dist: python-dateutil>=2.6.0
Provides-Extra: tests
Requires-Dist: pytest; extra == 'tests'
Requires-Dist: pytest-cov; extra == 'tests'
Requires-Dist: pytest-flake8; extra == 'tests'
Requires-Dist: pytest-profiling; extra == 'tests'
